text_vectorian/__init__.py
text_vectorian/bases.py
text_vectorian/char2vec.py
text_vectorian/config.yml
text_vectorian/default_bert_config.json
text_vectorian/sentencepiece.py
text_vectorian/sp_bert.py
text_vectorian/utils.py
text_vectorian-0.3.0.dist-info/LICENSE
text_vectorian-0.3.0.dist-info/METADATA
text_vectorian-0.3.0.dist-info/WHEEL
text_vectorian-0.3.0.dist-info/top_level.txt
text_vectorian-0.3.0.dist-info/RECORD
