Metadata-Version: 2.1
Name: text-vectorian
Version: 0.3.0
Summary: For getting token embedded vectors for NLP.
Home-page: https://github.com/lhideki/text-vectorian
Author: Hideki INOUE
Author-email: hideki@inoue-kobo.com
License: MIT
Platform: UNKNOWN
License-File: LICENSE
Requires-Dist: gensim
Requires-Dist: sentencepiece
Requires-Dist: keras
Requires-Dist: keras-bert
